userinterface/__init__.py
userinterface/userinterface.py
userinterface-0.0.8.dist-info/METADATA
userinterface-0.0.8.dist-info/WHEEL
userinterface-0.0.8.dist-info/top_level.txt
userinterface-0.0.8.dist-info/RECORD
