Metadata-Version: 2.1
Name: userinterface
Version: 0.0.8
Summary: userinteface description
Author-email: Ruud van der Ham <rt.van.der.ham@gmail.com>
Requires-Python: >=3.7
